csv2parquet/__init__.py
csv2parquet/__main__.py
csv2parquet/csv2parquet.py
csv2parquet/test_argparse.py
csv2parquet/test_write.py
csv2parquet-0.0.9.dist-info/METADATA
csv2parquet-0.0.9.dist-info/RECORD
csv2parquet-0.0.9.dist-info/WHEEL
csv2parquet-0.0.9.dist-info/entry_points.txt
csv2parquet-0.0.9.dist-info/top_level.txt
