Metadata-Version: 2.1
Name: csv2parquet
Version: 0.0.9
Summary: A tool to convert CSVs to Parquet files
Home-page: https://github.com/cldellow/csv2parquet
Author: Colin Dellow
Author-email: cldellow@cldellow.com
License: UNKNOWN
Platform: UNKNOWN
Classifier: Programming Language :: Python :: 3
Classifier: License :: OSI Approved :: Apache Software License
Classifier: Operating System :: OS Independent
